aryansindhi_outlier/__init__.py
aryansindhi_outlier/outlier_cmd.py
aryansindhi_101703110_outlier_cmd-1.0.3.dist-info/LICENSE
aryansindhi_101703110_outlier_cmd-1.0.3.dist-info/METADATA
aryansindhi_101703110_outlier_cmd-1.0.3.dist-info/WHEEL
aryansindhi_101703110_outlier_cmd-1.0.3.dist-info/entry_points.txt
aryansindhi_101703110_outlier_cmd-1.0.3.dist-info/top_level.txt
aryansindhi_101703110_outlier_cmd-1.0.3.dist-info/RECORD
