Metadata-Version: 2.1
Name: aryansindhi-101703110-outlier-cmd
Version: 1.0.3
Summary: A small package that removes outliers from a pandas dataframe
Home-page: https://github.com/aryansindhi18/Aryan_Sindhi_101703110_outlier_removal
Author: Aryan Sindhi
Author-email: asindhi_be17@thapar.edu
License: UNKNOWN
Platform: UNKNOWN
Classifier: Programming Language :: Python :: 3
Classifier: License :: OSI Approved :: MIT License
Classifier: Operating System :: OS Independent
Requires-Python: >=3.6
